Metadata-Version: 2.1
Name: distributions-dr99
Version: 0.1
Summary: Gaussian distributions
License: UNKNOWN
Platform: UNKNOWN
